{
    "id": "water-layer",
    "type": "triangle",
    "style": "water",
    "visible": true,
    "selectable": false,
    "skip": false,
    "data": [
        {
            "geometry": {
                "coordinates": [
                    40.66291,
                    -73.9717997,
                    40.6629141,
                    -73.9718319,
                    40.6627865,
                    -73.9718416,
                    40.6626536,
                    -73.9718963,
                    40.6625784,
                    -73.9718909,
                    40.6624013,
                    -73.9718266,
                    40.6623047,
                    -73.9717043,
                    40.6622331,
                    -73.9715326,
                    40.662194,
                    -73.9713782,
                    40.6621614,
                    -73.9711893,
                    40.662181,
                    -73.970949,
                    40.6622396,
                    -73.9708117,
                    40.6623307,
                    -73.970743,
                    40.6624935,
                    -73.9707173,
                    40.6627018,
                    -73.9707258,
                    40.6628255,
                    -73.9707688,
                    40.6629167,
                    -73.970846,
                    40.6630565,
                    -73.9709951,
                    40.6630483,
                    -73.9711292,
                    40.6630199,
                    -73.9712418,
                    40.6629954,
                    -73.9713545,
                    40.6629954,
                    -73.9714832,
                    40.6629507,
                    -73.9715744,
                    40.6628978,
                    -73.971671,
                    40.6628516,
                    -73.971773,
                    40.6628774,
                    -73.971789,
                    40.66291,
                    -73.9717997,
                    40.6629263,
                    -73.9714189,
                    40.6629181,
                    -73.9713384,
                    40.6628734,
                    -73.971274,
                    40.6628449,
                    -73.9712526,
                    40.6627838,
                    -73.9712472,
                    40.6627676,
                    -73.9712847,
                    40.6627676,
                    -73.9713384,
                    40.662796,
                    -73.971392,
                    40.6628164,
                    -73.9714242,
                    40.6628164,
                    -73.9714671,
                    40.662853,
                    -73.9715208,
                    40.6628937,
                    -73.9715369,
                    40.6629222,
                    -73.9715101,
                    40.6629263,
                    -73.9714618,
                    40.6629263,
                    -73.9714189
                ],
                "indices": [
                    23,
                    22,
                    21,
                    19,
                    18,
                    17,
                    17,
                    16,
                    15,
                    15,
                    14,
                    13,
                    13,
                    12,
                    11,
                    11,
                    10,
                    9,
                    9,
                    33,
                    32,
                    36,
                    35,
                    34,
                    34,
                    33,
                    9,
                    9,
                    8,
                    7,
                    7,
                    6,
                    5,
                    5,
                    4,
                    3,
                    2,
                    1,
                    26,
                    23,
                    21,
                    20,
                    20,
                    19,
                    17,
                    17,
                    15,
                    13,
                    13,
                    11,
                    9,
                    9,
                    32,
                    31,
                    36,
                    34,
                    9,
                    9,
                    7,
                    5,
                    5,
                    3,
                    2,
                    2,
                    26,
                    25,
                    24,
                    23,
                    20,
                    20,
                    17,
                    13,
                    13,
                    9,
                    31,
                    37,
                    36,
                    9,
                    9,
                    5,
                    2,
                    2,
                    25,
                    24,
                    13,
                    31,
                    30,
                    37,
                    9,
                    2,
                    2,
                    24,
                    20,
                    20,
                    13,
                    30,
                    38,
                    37,
                    2,
                    20,
                    30,
                    29,
                    39,
                    38,
                    2,
                    20,
                    29,
                    28,
                    39,
                    2,
                    20,
                    20,
                    28,
                    41,
                    40,
                    39,
                    20,
                    20,
                    41,
                    40
                ]
            }
        },
        {
            "geometry": {
                "coordinates": [
                    40.6629141,
                    -73.9718319,
                    40.66291,
                    -73.9717997,
                    40.662967,
                    -73.9717836,
                    40.6630402,
                    -73.97173,
                    40.6631381,
                    -73.9716528,
                    40.6631836,
                    -73.9715155,
                    40.6632422,
                    -73.9714297,
                    40.6632813,
                    -73.9713267,
                    40.6633088,
                    -73.9712687,
                    40.6633535,
                    -73.9711667,
                    40.6633269,
                    -73.9711035,
                    40.6632683,
                    -73.9709747,
                    40.6632487,
                    -73.9708546,
                    40.6632683,
                    -73.9707516,
                    40.6633291,
                    -73.9707322,
                    40.663405,
                    -73.9707516,
                    40.6635244,
                    -73.9707483,
                    40.6636099,
                    -73.9707376,
                    40.6636669,
                    -73.9707751,
                    40.6637442,
                    -73.9708127,
                    40.663793,
                    -73.9708234,
                    40.6637964,
                    -73.9708551,
                    40.6638011,
                    -73.9708985,
                    40.6637604,
                    -73.970979,
                    40.6636831,
                    -73.9710326,
                    40.6635938,
                    -73.9712408,
                    40.6635352,
                    -73.9713438,
                    40.6634375,
                    -73.9715241,
                    40.6633269,
                    -73.9716871,
                    40.663203,
                    -73.9717836,
                    40.6630565,
                    -73.9718158,
                    40.6629141,
                    -73.9718319
                ],
                "indices": [
                    1,
                    31,
                    30,
                    30,
                    29,
                    28,
                    28,
                    27,
                    26,
                    26,
                    25,
                    24,
                    24,
                    23,
                    22,
                    21,
                    20,
                    19,
                    18,
                    17,
                    16,
                    15,
                    14,
                    13,
                    13,
                    12,
                    11,
                    8,
                    7,
                    6,
                    6,
                    5,
                    4,
                    2,
                    1,
                    30,
                    30,
                    28,
                    26,
                    24,
                    22,
                    21,
                    21,
                    19,
                    18,
                    18,
                    16,
                    15,
                    15,
                    13,
                    11,
                    9,
                    8,
                    6,
                    3,
                    2,
                    30,
                    30,
                    26,
                    24,
                    24,
                    21,
                    18,
                    18,
                    15,
                    11,
                    4,
                    3,
                    30,
                    30,
                    24,
                    18,
                    18,
                    11,
                    10,
                    4,
                    30,
                    18,
                    18,
                    10,
                    9,
                    6,
                    4,
                    18,
                    18,
                    9,
                    6
                ]
            }
        },
        {
            "geometry": {
                "coordinates": [
                    40.6641404,
                    -73.9696968,
                    40.6640605,
                    -73.9696857,
                    40.664048755200824,
                    -73.9696608,
                    40.66416265726141,
                    -73.9696608,
                    40.6641404,
                    -73.9696968
                ],
                "indices": [
                    1,
                    4,
                    3,
                    3,
                    2,
                    1
                ]
            }
        },
        {
            "geometry": {
                "coordinates": [
                    40.6769207,
                    -73.9898742,
                    40.6769522,
                    -73.9899423,
                    40.6769082,
                    -73.9899773,
                    40.6768184,
                    -73.9900487,
                    40.676787,
                    -73.9899827,
                    40.6768628,
                    -73.9899212,
                    40.6768775,
                    -73.9899092,
                    40.6769207,
                    -73.9898742
                ],
                "indices": [
                    1,
                    7,
                    6,
                    5,
                    4,
                    3,
                    3,
                    2,
                    1,
                    1,
                    6,
                    5,
                    5,
                    3,
                    1
                ]
            }
        },
        {
            "geometry": {
                "coordinates": [
                    40.6812433,
                    -73.9705673,
                    40.6811964,
                    -73.9705832,
                    40.6811777,
                    -73.9704869,
                    40.6812246,
                    -73.970471,
                    40.6812433,
                    -73.9705673
                ],
                "indices": [
                    1,
                    4,
                    3,
                    3,
                    2,
                    1
                ]
            }
        },
        {
            "geometry": {
                "coordinates": [
                    40.663255,
                    -73.9739742,
                    40.6632367,
                    -73.9738675,
                    40.6632582,
                    -73.9737227,
                    40.6632933,
                    -73.9736845,
                    40.6633378,
                    -73.9736898,
                    40.6633793,
                    -73.9737475,
                    40.6633909,
                    -73.9738113,
                    40.6633365,
                    -73.9739439,
                    40.663255,
                    -73.9739742
                ],
                "indices": [
                    1,
                    8,
                    7,
                    7,
                    6,
                    5,
                    5,
                    4,
                    3,
                    3,
                    2,
                    1,
                    1,
                    7,
                    5,
                    5,
                    3,
                    1
                ]
            }
        },
        {
            "geometry": {
                "coordinates": [
                    40.67499277832883,
                    -73.9930068,
                    40.6746333,
                    -73.9922627,
                    40.6747858,
                    -73.9921366,
                    40.6750198,
                    -73.9926221,
                    40.6751113,
                    -73.9925497,
                    40.67532489990845,
                    -73.9930068,
                    40.67499277832883,
                    -73.9930068
                ],
                "indices": [
                    1,
                    6,
                    5,
                    5,
                    4,
                    3,
                    3,
                    2,
                    1,
                    1,
                    5,
                    3
                ]
            }
        },
        {
            "geometry": {
                "coordinates": [
                    40.67591057636093,
                    -73.9930068,
                    40.6758619,
                    -73.992783,
                    40.6757806,
                    -73.992327,
                    40.6756585,
                    -73.9915411,
                    40.6755445,
                    -73.9910129,
                    40.6755323,
                    -73.9909483,
                    40.6755243,
                    -73.9909108,
                    40.6754978,
                    -73.9908357,
                    40.6754897,
                    -73.9907714,
                    40.6754673,
                    -73.9907472,
                    40.6754408,
                    -73.9907284,
                    40.6753819,
                    -73.9906989,
                    40.6753391,
                    -73.9906775,
                    40.6753005,
                    -73.9906587,
                    40.6748367,
                    -73.9904817,
                    40.6747858,
                    -73.9904441,
                    40.6747594,
                    -73.9904066,
                    40.674735,
                    -73.990361,
                    40.6744136,
                    -73.9896314,
                    40.6741389,
                    -73.9890762,
                    40.6741267,
                    -73.9890867,
                    40.6741078,
                    -73.9890481,
                    40.6741867,
                    -73.9889826,
                    40.6741608,
                    -73.988928,
                    40.6743397,
                    -73.9887818,
                    40.6746332,
                    -73.9894159,
                    40.6748102,
                    -73.9897977,
                    40.6749609,
                    -73.9901048,
                    40.675034,
                    -73.9902537,
                    40.6750686,
                    -73.9903073,
                    40.6755466,
                    -73.990487,
                    40.6755609,
                    -73.9904897,
                    40.6755792,
                    -73.9904817,
                    40.6758131,
                    -73.990302,
                    40.6759735,
                    -73.9901662,
                    40.6766817,
                    -73.989567,
                    40.6772757,
                    -73.9890494,
                    40.6776479,
                    -73.9890252,
                    40.6782114,
                    -73.9889904,
                    40.6782155,
                    -73.9890118,
                    40.6782248,
                    -73.9890068,
                    40.6782704,
                    -73.9889823,
                    40.6785713,
                    -73.9887892,
                    40.6792629,
                    -73.9883064,
                    40.6800562,
                    -73.9877914,
                    40.6800949,
                    -73.9877673,
                    40.6801071,
                    -73.9877405,
                    40.6811018,
                    -73.9870619,
                    40.6816347,
                    -73.9867051,
                    40.6817526,
                    -73.9870189,
                    40.6807292,
                    -73.9877058,
                    40.6802424,
                    -73.9880342,
                    40.6801841,
                    -73.9880641,
                    40.6801525,
                    -73.9880903,
                    40.6795134,
                    -73.988523,
                    40.6793118,
                    -73.9886631,
                    40.6788891,
                    -73.9889466,
                    40.6783477,
                    -73.9893203,
                    40.6782293,
                    -73.9893297,
                    40.6781066,
                    -73.9893409,
                    40.6775686,
                    -73.98939,
                    40.6774542,
                    -73.9894065,
                    40.6773449,
                    -73.9894222,
                    40.6768296,
                    -73.9898497,
                    40.6768253,
                    -73.9898675,
                    40.6768357,
                    -73.989891,
                    40.6767722,
                    -73.989944,
                    40.6767638,
                    -73.9899256,
                    40.6767475,
                    -73.9899198,
                    40.6757989,
                    -73.9907097,
                    40.675925,
                    -73.9914741,
                    40.6759392,
                    -73.9914526,
                    40.6760857,
                    -73.9924906,
                    40.6760948,
                    -73.9925728,
                    40.6761081,
                    -73.9926918,
                    40.6761589,
                    -73.9929869,
                    40.67616219512987,
                    -73.9930068,
                    40.67591057636093,
                    -73.9930068
                ],
                "indices": [
                    1,
                    77,
                    76,
                    76,
                    75,
                    74,
                    73,
                    72,
                    71,
                    67,
                    66,
                    65,
                    62,
                    61,
                    60,
                    60,
                    59,
                    58,
                    58,
                    57,
                    56,
                    56,
                    55,
                    54,
                    54,
                    53,
                    52,
                    52,
                    51,
                    50,
                    50,
                    49,
                    48,
                    48,
                    47,
                    46,
                    45,
                    44,
                    43,
                    41,
                    40,
                    39,
                    39,
                    38,
                    37,
                    37,
                    36,
                    35,
                    35,
                    34,
                    33,
                    25,
                    24,
                    23,
                    22,
                    21,
                    20,
                    18,
                    17,
                    16,
                    16,
                    15,
                    14,
                    8,
                    7,
                    6,
                    5,
                    4,
                    3,
                    3,
                    2,
                    1,
                    1,
                    76,
                    74,
                    74,
                    73,
                    71,
                    68,
                    67,
                    65,
                    60,
                    58,
                    56,
                    56,
                    54,
                    52,
                    52,
                    50,
                    48,
                    48,
                    46,
                    45,
                    45,
                    43,
                    42,
                    39,
                    37,
                    35,
                    26,
                    25,
                    23,
                    22,
                    20,
                    19,
                    18,
                    16,
                    14,
                    3,
                    1,
                    74,
                    74,
                    71,
                    70,
                    68,
                    65,
                    64,
                    62,
                    60,
                    56,
                    56,
                    52,
                    48,
                    27,
                    26,
                    23,
                    22,
                    19,
                    18,
                    18,
                    14,
                    13,
                    5,
                    3,
                    74,
                    74,
                    70,
                    69,
                    68,
                    64,
                    63,
                    56,
                    48,
                    45,
                    28,
                    27,
                    23,
                    22,
                    18,
                    13,
                    6,
                    5,
                    74,
                    69,
                    68,
                    63,
                    56,
                    45,
                    42,
                    29,
                    28,
                    23,
                    8,
                    6,
                    74,
                    56,
                    42,
                    41,
                    29,
                    23,
                    22,
                    8,
                    74,
                    69,
                    56,
                    41,
                    39,
                    29,
                    22,
                    13,
                    9,
                    8,
                    69,
                    62,
                    56,
                    39,
                    30,
                    29,
                    13,
                    10,
                    9,
                    69,
                    62,
                    39,
                    35,
                    31,
                    30,
                    13,
                    11,
                    10,
                    69,
                    63,
                    62,
                    35,
                    32,
                    31,
                    13,
                    12,
                    11,
                    69,
                    69,
                    63,
                    35,
                    32,
                    13,
                    12,
                    69,
                    35,
                    33,
                    33,
                    32,
                    12,
                    12,
                    69,
                    33
                ]
            }
        }
    ]
}